[
    {
        "id": 1,
        "doYouWantToShowThis": "yes",
        "link": "https://github.com/diwas7777/LinkTree",
        "icons": "fa fa-chrome",
        "contentToShow": "Portfolio"
    },
    {
        "id": 2,
        "doYouWantToShowThis": "yes",
        "link": "#",
        "icons": "fa fa-shopping-cart",
        "contentToShow": "Shop"
    },
    {
        "id": 3,
        "doYouWantToShowThis": "yes",
        "link": "#",
        "icons": "fa fa-edit",
        "contentToShow": "Blog"
    },
    {
        "id": 4,
        "doYouWantToShowThis": "yes",
        "link": "#",
        "icons": "fa fa-facebook",
        "contentToShow": "Facebook"
    },
    {
        "id": 5,
        "doYouWantToShowThis": "yes",
        "link": "#",
        "icons": "fa fa-instagram",
        "contentToShow": "Instagram"
    },
    {
        "id": 6,
        "doYouWantToShowThis": "yes",
        "link": "#",
        "icons": "fa fa-twitter-square",
        "contentToShow": "Twitter"
    },
    {
        "id": 7,
        "doYouWantToShowThis": "yes",
        "link": "#",
        "icons": "fa fa-gitHub",
        "contentToShow": "GitHub"
    },
    {
        "id": 8,
        "doYouWantToShowThis": "yes",
        "link": "#",
        "icons": "fa fa-telegram",
        "contentToShow": "Telegram"
    }
]
